<annotation>
	<folder>infusomat_space</folder>
	<filename>img_20.jpg</filename>
	<path>C:\Users\Brian-Gloekler\Desktop\Hackathon\Images\infusomat_space\img_20.jpg</path>
	<source>
		<database>Unknown</database>
	</source>
	<size>
		<width>350</width>
		<height>350</height>
		<depth>3</depth>
	</size>
	<segmented>0</segmented>
	<object>
		<name>BBraun Infusomat Space</name>
		<pose>Unspecified</pose>
		<truncated>0</truncated>
		<difficult>0</difficult>
		<bndbox>
			<xmin>69</xmin>
			<ymin>171</ymin>
			<xmax>224</xmax>
			<ymax>248</ymax>
		</bndbox>
	</object>
</annotation>
